solace_event_portal_designer_mcp/__init__.py
solace_event_portal_designer_mcp/server.py
solace_event_portal_designer_mcp/data/ep-designer.json
solace_event_portal_designer_mcp-0.1.2.dist-info/METADATA
solace_event_portal_designer_mcp-0.1.2.dist-info/WHEEL
solace_event_portal_designer_mcp-0.1.2.dist-info/entry_points.txt
solace_event_portal_designer_mcp-0.1.2.dist-info/RECORD
