Metadata-Version: 2.4
Name: solace-event-portal-designer-mcp
Version: 0.1.2
Summary: Model Context Protocol (MCP) server for Solace Event Portal Designer API
Project-URL: Homepage, https://github.com/SolaceLabs/solace-platform-mcp
Project-URL: Repository, https://github.com/SolaceLabs/solace-platform-mcp
Project-URL: Issues, https://github.com/SolaceLabs/solace-platform-mcp/issues
Author-email: Solace Corporation <support@solace.com>
License: Apache-2.0
Keywords: event-portal,mcp,model-context-protocol,solace
Classifier: Intended Audience :: Developers
Classifier: License :: OSI Approved :: Apache Software License
Classifier: Programming Language :: Python :: 3
Classifier: Programming Language :: Python :: 3.10
Classifier: Programming Language :: Python :: 3.11
Classifier: Programming Language :: Python :: 3.12
Classifier: Programming Language :: Python :: 3.13
Requires-Python: >=3.10
Requires-Dist: fastmcp<2.14,>=2.13.3
Provides-Extra: dev
Requires-Dist: pytest-cov>=4.0.0; extra == 'dev'
Requires-Dist: pytest>=8.0.0; extra == 'dev'
